p5widget/__init__.py
p5widget/p5widget.js
p5widget/py.typed
p5widget-0.1.0.dist-info/METADATA
p5widget-0.1.0.dist-info/WHEEL
p5widget-0.1.0.dist-info/licenses/LICENSE
p5widget-0.1.0.dist-info/RECORD
