Metadata-Version: 2.4
Name: p5widget
Version: 0.1.0
Summary: An p5.js anywidget for notebooks
Project-URL: home, https://github.com/georgeyk/p5-widget
Author-email: "George Y. Kussumoto" <georgeyk.dev@gmail.com>
License-File: LICENSE
Keywords: notebook,p5,p5js,widget
Classifier: Intended Audience :: Developers
Classifier: License :: OSI Approved :: MIT License
Classifier: Programming Language :: Python :: 3
Requires-Python: >=3.11.5
Requires-Dist: anywidget>=0.9.18
Requires-Dist: traitlets>=5.14.3
